redis_session_manager/__init__.py
redis_session_manager/session_manager.py
strands_redis_session_manager-0.1.0.dist-info/licenses/LICENSE
strands_redis_session_manager-0.1.0.dist-info/METADATA
strands_redis_session_manager-0.1.0.dist-info/WHEEL
strands_redis_session_manager-0.1.0.dist-info/top_level.txt
strands_redis_session_manager-0.1.0.dist-info/RECORD
