Metadata-Version: 2.4
Name: strands-redis-session-manager
Version: 0.1.0
Summary: Redis-based session management for persisting and managing agent sessions in the Strands Agents SDK
Author-email: lekhnath <inboxlekhnath@gmail.com>
License-Expression: MIT
Project-URL: Homepage, https://github.com/lekhnath/strands-redis-session-manager
Project-URL: Documentation, https://github.com/lekhnath/strands-redis-session-manager#readme
Project-URL: Repository, https://github.com/lekhnath/strands-redis-session-manager
Project-URL: Issues, https://github.com/lekhnath/strands-redis-session-manager/issues
Keywords: strands,agents,session,redis,ai,llm,memory
Requires-Python: >=3.12
License-File: LICENSE
Requires-Dist: redis>=7.0.1
Requires-Dist: strands-agents>=1.16.0
Dynamic: license-file
